textdiversity/__init__.py
textdiversity/metric.py
textdiversity/utils.py
textdiversity/search/__init__.py
textdiversity/search/textfetch.py
textdiversity/similarities/__init__.py
textdiversity/similarities/amrsim.py
textdiversity/similarities/phoneme_similarities.csv
textdiversity/text_diversities/__init__.py
textdiversity/text_diversities/morphological.py
textdiversity/text_diversities/phonological.py
textdiversity/text_diversities/semantic.py
textdiversity/text_diversities/syntactic.py
textdiversity-0.0.29.dist-info/METADATA
textdiversity-0.0.29.dist-info/WHEEL
textdiversity-0.0.29.dist-info/top_level.txt
textdiversity-0.0.29.dist-info/RECORD
