Metadata-Version: 2.1
Name: textdiversity
Version: 0.0.29
Summary: A family of textual diversity metrics
Home-page: https://github.com/fabriceyhc/TextDiversity
Author: Fabrice Harel-Canada
Author-email: fabriceyhc@gmail.com
Project-URL: Bug Tracker, https://github.com/fabriceyhc/TextDiversity/issues
Classifier: Programming Language :: Python :: 3
Classifier: License :: OSI Approved :: MIT License
Classifier: Operating System :: OS Independent
Requires-Python: >=3.8
Requires-Dist: amrlib
Requires-Dist: benepar
Requires-Dist: biopython
Requires-Dist: cadences
Requires-Dist: faiss-cpu
Requires-Dist: karateclub
Requires-Dist: networkx
Requires-Dist: phonemizer
Requires-Dist: pyemd
Requires-Dist: scikit-learn
Requires-Dist: scipy
Requires-Dist: seaborn
Requires-Dist: spacy
Requires-Dist: torch
Requires-Dist: transformers
Requires-Dist: sentence-transformers
Requires-Dist: stanza
Requires-Dist: unidecode
Requires-Dist: zss
